Metadata-Version: 1.0
Name: kjy-HelloWorld
Version: 1.0
Summary: This is a test of the setup
Home-page: https://github.com/kangjianyu/HelloWorld.git
Author: kjy
Author-email: 609363537@qq.com
License: UNKNOWN
Platform: UNKNOWN
